[{"_id":1,"name":"Okunade Sherif","email":"lawdshev@gmail.com","address":"23,olawale imam gbagada","phone":"07064413800","tickets":[{"_orderId":"xxx","typeOfOrder":"Dry Cleaning","numberOfClothes":30,"price":3000,"pickUpName":"self","pickUpAddress":"same","phoneNumber":"same"}]},{"_id":2,"name":"ashraf gymmore deen","email":"gym@gmail.com","tickets":[{"_orderId":"xxx","typeOfOrder":"Flat Ironing","numberOfClothes":40,"price":4000,"pickUpName":"rasheeda deen","pickUpAddress":"23, imam gbagada","phoneNumber":"08177945552"},{"_orderId":"xxx","typeOfOrder":"Flat Ironing","numberOfClothes":40,"price":4000,"pickUpName":"rasheeda deen","pickUpAddress":"23, imam gbagada","phoneNumber":"08177945552"},{"_orderId":"xxx","pickUpName":"rasheeda deen","pickUpAddress":"23, imam gbagada","phoneNumber":"08177945552"}],"address":"ashraf gymmore deen","phone":"ashraf gymmore deen"},{"_id":3,"name":"Sherif Okunade","email":"shokobarbie@gmail.com","address":"23, olawale dawodu street","phone":"+2347064413800","tickets":[]},{"_id":4,"name":"mad max","email":"madmax@gmail.com","address":"27, olawale dawodu street","phone":"2237064413800","tickets":[]},{"_id":5,"name":"madmax","email":"madmax@gmail.com","address":"shevy suite","phone":"8177950542","tickets":[]},"{\"_id\":6,\"name\":\"Sherif Okunade\",\"email\":\"shokobarbie2002@gmail.com\",\"address\":\"23, olawale dawodu street\",\"phone\":\"+2347064413800\",\"tickets\":[]}","{\"_id\":7,\"name\":\"madmax rexo\",\"email\":\"madmax99@gmail.com\",\"address\":\"shevy suite hotel\",\"phone\":\"8177950542\",\"tickets\":[]}"]